rt_sports_scrapers/Google_Sheet.py
rt_sports_scrapers/Reddit_Match_Day_Scraper_Cricket.py
rt_sports_scrapers/Twitter_News_Scraper.py
rt_sports_scrapers/__init__.py
rt_sports_scrapers/reddit_scraper.py
rt_sports_scrapers-0.0.9.dist-info/METADATA
rt_sports_scrapers-0.0.9.dist-info/WHEEL
rt_sports_scrapers-0.0.9.dist-info/top_level.txt
rt_sports_scrapers-0.0.9.dist-info/RECORD
