Metadata-Version: 2.1
Name: rt-sports-scrapers
Version: 0.0.9
Summary: Reddit,Twitter,Scrapers
Author: Mathew Mammen Jacob
Author-email: <mathew.mammenjacob@gmail.com>
License: UNKNOWN
Keywords: python,first package,Scrappers
Platform: UNKNOWN
Classifier: Development Status :: 3 - Alpha
Classifier: Intended Audience :: Education
Classifier: Programming Language :: Python :: 2
Classifier: Programming Language :: Python :: 3
Classifier: Operating System :: MacOS :: MacOS X
Classifier: Operating System :: Microsoft :: Windows
Requires-Dist: gspread
Requires-Dist: gspread-dataframe
Requires-Dist: twint-fork
